{"assets":{"D057EC467AB16BE7D9B8D469C0A49C62":{"type":"texture","index":0,"assetRequest":{"type":"slide","state":"contents","slide":"none"},"url":{"native":"assets\/CF5A7240-A15A-4D0E-B324-1B3A077A8104.pdf"},"width":1920,"height":1080},"0619399C9A7F94CE186AB245D77E7C49":{"type":"texture","index":1,"assetRequest":{"type":"slide","state":"contents","slide":"none"},"url":{"native":"assets\/CF5A7240-A15A-4D0E-B324-1B3A077A8104.pdf"},"width":1920,"height":1080}},"events":[{"effects":[{"beginTime":0,"baseLayer":{"animations":[],"initialState":{"affineTransform":[1,0,0,1,0,0],"masksToBounds":false,"rotation":0,"scale":1,"position":{"pointX":960,"pointY":540},"width":1920,"sublayerTransform":[1,0,0,0,0,1,0,0,0,0,1,0,0,0,0,1],"contentsRect":{"y":0,"x":0,"width":1,"height":1},"opacity":1,"edgeAntialiasingMask":251658240,"height":1080,"hidden":false,"anchorPoint":{"pointX":0.5,"pointY":0.5}},"objectID":"0","layers":[{"animations":[],"initialState":{"affineTransform":[1,0,0,1,0,0],"masksToBounds":false,"rotation":0,"scale":1,"position":{"pointX":960,"pointY":540},"width":1920,"sublayerTransform":[1,0,0,0,0,1,0,0,0,0,1,-0.00035007912466775983,0,0,0,1],"contentsRect":{"y":0,"x":0,"width":1,"height":1},"opacity":1,"edgeAntialiasingMask":251658240,"height":1080,"hidden":false,"anchorPoint":{"pointX":0.5,"pointY":0.5}},"layers":[{"animations":[{"repeatCount":0,"timingControlPoint2y":0.9959721565246582,"from":{"pointX":2880,"pointY":540},"timingFunction":"custom","timeOffset":0,"autoreverses":false,"timingControlPoint1x":0.49705871939659119,"fillMode":"both","property":"position","duration":0.75,"beginTime":0,"timingControlPoint2x":0.49811732769012451,"timingControlPoint1y":0,"to":{"pointX":960,"pointY":540}}],"layers":[],"texturedRectangle":{"isBackgroundTexture":false,"singleTextureOpacity":1,"textureType":0,"textBaseline":0,"textXHeight":0,"isVerticalText":false},"initialState":{"affineTransform":[1,0,0,1,0,0],"masksToBounds":false,"rotation":0,"scale":1,"position":{"pointX":960,"pointY":540},"width":1920,"sublayerTransform":[1,0,0,0,0,1,0,0,0,0,1,0,0,0,0,1],"contentsRect":{"y":0,"x":0,"width":1,"height":1},"opacity":1,"edgeAntialiasingMask":0,"height":1080,"hidden":false,"anchorPoint":{"pointX":0.5,"pointY":0.5}},"texture":"0619399C9A7F94CE186AB245D77E7C49"},{"animations":[{"repeatCount":0,"timingControlPoint2y":0.9959721565246582,"from":{"pointX":960,"pointY":540},"timingFunction":"custom","timeOffset":0,"autoreverses":false,"timingControlPoint1x":0.49705871939659119,"fillMode":"both","property":"position","duration":0.75,"beginTime":0,"timingControlPoint2x":0.49811732769012451,"timingControlPoint1y":0,"to":{"pointX":-960,"pointY":540}}],"layers":[],"texturedRectangle":{"isBackgroundTexture":false,"singleTextureOpacity":1,"textureType":0,"textBaseline":0,"textXHeight":0,"isVerticalText":false},"initialState":{"affineTransform":[1,0,0,1,0,0],"masksToBounds":false,"rotation":0,"scale":1,"position":{"pointX":960,"pointY":540},"width":1920,"sublayerTransform":[1,0,0,0,0,1,0,0,0,0,1,0,0,0,0,1],"contentsRect":{"y":0,"x":0,"width":1,"height":1},"opacity":1,"edgeAntialiasingMask":0,"height":1080,"hidden":false,"anchorPoint":{"pointX":0.5,"pointY":0.5}},"texture":"D057EC467AB16BE7D9B8D469C0A49C62"}]}]},"effects":[],"duration":0.75,"type":"transition","attributes":{"direction":12},"name":"apple:push","objectID":"0"}],"automaticPlay":false,"hyperlinks":[],"accessibility":[{"text":"DEMO","targetRectangle":{"y":172.99667358398438,"x":676.00000095367432,"width":568,"height":236.1986083984375}},{"text":"CPM","targetRectangle":{"y":493.77552795410156,"x":897.5049991607666,"width":124.99000000000001,"height":68.317596435546875}},{"text":"Widgets","targetRectangle":{"y":838.68574523925781,"x":857.28199672698975,"width":205.43599999999992,"height":68.317596435546875}},{"text":"Glue","targetRectangle":{"y":608.74555969238281,"x":902.52199959754944,"width":114.95600000000002,"height":68.317596435546875}},{"text":"TypeScript","targetRectangle":{"y":723.71565246582031,"x":828.91999673843384,"width":262.16000000000008,"height":68.317596435546875}}],"baseLayer":{"animations":[],"initialState":{"affineTransform":[1,0,0,1,0,0],"masksToBounds":false,"rotation":0,"scale":1,"position":{"pointX":960,"pointY":540},"width":1920,"sublayerTransform":[1,0,0,0,0,1,0,0,0,0,1,0,0,0,0,1],"contentsRect":{"y":0,"x":0,"width":1,"height":1},"opacity":1,"edgeAntialiasingMask":251658240,"height":1080,"hidden":false,"anchorPoint":{"pointX":0.5,"pointY":0.5}},"objectID":"0","layers":[{"animations":[],"initialState":{"affineTransform":[1,0,0,1,0,0],"masksToBounds":false,"rotation":0,"scale":1,"position":{"pointX":960,"pointY":540},"width":1920,"sublayerTransform":[1,0,0,0,0,1,0,0,0,0,1,-0.00035007912466775983,0,0,0,1],"contentsRect":{"y":0,"x":0,"width":1,"height":1},"opacity":1,"edgeAntialiasingMask":251658240,"height":1080,"hidden":false,"anchorPoint":{"pointX":0.5,"pointY":0.5}},"layers":[{"animations":[],"layers":[],"texturedRectangle":{"isBackgroundTexture":false,"singleTextureOpacity":1,"textureType":0,"textBaseline":0,"textXHeight":0,"isVerticalText":false},"initialState":{"affineTransform":[1,0,0,1,0,0],"masksToBounds":false,"rotation":0,"scale":1,"position":{"pointX":960,"pointY":540},"width":1920,"sublayerTransform":[1,0,0,0,0,1,0,0,0,0,1,0,0,0,0,1],"contentsRect":{"y":0,"x":0,"width":1,"height":1},"opacity":1,"edgeAntialiasingMask":0,"height":1080,"hidden":false,"anchorPoint":{"pointX":0.5,"pointY":0.5}},"texture":"D057EC467AB16BE7D9B8D469C0A49C62"}]}]}}]}